<?xml version="1.0" encoding="UTF-8" ?>
<PhysicalTable mdsid="m80c8f851-0bb9-0000-714b-e31d00000000" name="WC_DPRTMNT_INTRST_F" xmlns:xsi="http://www.w3.org/2001/XMLSchema-instance" xmlns="http://www.oracle.com/obis/repository" type="none" x="172" y="50" maxConn="0" containerRef="/oracle/bi/server/base/Schema/80c67bb1-0bd3-0000-714b-e31d00000000.xml#m80c67bb1-0bd3-0000-714b-e31d00000000">
<PhysicalColumn mdsid="m80c8f853-0bbb-0000-714b-e31d00000000" name="CONTACT_WID" dataType="DOUBLE" precision="10" specialType="none">
</PhysicalColumn>
<PhysicalColumn mdsid="m80c8f855-0bbb-0000-714b-e31d00000000" name="DATASOURCE_NUM_ID" dataType="DOUBLE" precision="10" specialType="none">
</PhysicalColumn>
<PhysicalColumn mdsid="m80c8f857-0bbb-0000-714b-e31d00000000" name="DPRTMNT_INTRST_ATTR_WID" dataType="DOUBLE" precision="10" specialType="none">
</PhysicalColumn>
<PhysicalColumn mdsid="m80c8f859-0bbb-0000-714b-e31d00000000" name="DPRTMNT_INTRST_WID" dataType="DOUBLE" precision="10" specialType="none">
</PhysicalColumn>
<PhysicalColumn mdsid="m80c8f85b-0bbb-0000-714b-e31d00000000" name="ETL_PROC_WID" dataType="DOUBLE" precision="10" specialType="none">
</PhysicalColumn>
<PhysicalColumn mdsid="m80c8f85d-0bbb-0000-714b-e31d00000000" name="INTEGRATION_ID" dataType="VARCHAR" precision="80" specialType="none">
</PhysicalColumn>
<PhysicalColumn mdsid="m80c8f85f-0bbb-0000-714b-e31d00000000" name="ORG_WID" dataType="DOUBLE" precision="10" specialType="none">
</PhysicalColumn>
<PhysicalColumn mdsid="m80c8f861-0bbb-0000-714b-e31d00000000" name="OWNING_PARTY_WID" dataType="DOUBLE" precision="10" specialType="none">
</PhysicalColumn>
<PhysicalColumn mdsid="m80c8f863-0bbb-0000-714b-e31d00000000" name="ROW_WID" dataType="DOUBLE" precision="10" specialType="none">
</PhysicalColumn>
</PhysicalTable>