<?xml version="1.0" encoding="UTF-8" ?>
<PhysicalTable mdsid="m80ca360a-0bb9-0000-714b-e31d00000000" name="WC_RELATIONAL_HIER_F" xmlns:xsi="http://www.w3.org/2001/XMLSchema-instance" xmlns="http://www.oracle.com/obis/repository" type="none" x="411" y="250" maxConn="0" containerRef="/oracle/bi/server/base/Schema/80c67bb1-0bd3-0000-714b-e31d00000000.xml#m80c67bb1-0bd3-0000-714b-e31d00000000">
<PhysicalColumn mdsid="m80ca360b-0bbb-0000-714b-e31d00000000" name="CANVASSER_FLG" dataType="CHAR" precision="1" nullable="true" specialType="none">
</PhysicalColumn>
<PhysicalColumn mdsid="m80ca360c-0bbb-0000-714b-e31d00000000" name="CREATED_BY" dataType="VARCHAR" precision="100" nullable="true" specialType="none">
</PhysicalColumn>
<PhysicalColumn mdsid="m80ca360d-0bbb-0000-714b-e31d00000000" name="CREATED_DT" dataType="DATE" nullable="true" specialType="none">
</PhysicalColumn>
<PhysicalColumn mdsid="m80ca360e-0bbb-0000-714b-e31d00000000" name="DATASOURCE_NUM_ID" dataType="DOUBLE" precision="10" specialType="none">
</PhysicalColumn>
<PhysicalColumn mdsid="m80ca360f-0bbb-0000-714b-e31d00000000" name="END_DT" dataType="DATE" nullable="true" specialType="none">
</PhysicalColumn>
<PhysicalColumn mdsid="m80ca3610-0bbb-0000-714b-e31d00000000" name="ETL_PROC_WID" dataType="DOUBLE" precision="10" specialType="none">
</PhysicalColumn>
<PhysicalColumn mdsid="m80ca3611-0bbb-0000-714b-e31d00000000" name="FROM_EMP_WID" dataType="DOUBLE" precision="10" specialType="none">
</PhysicalColumn>
<PhysicalColumn mdsid="m80ca3612-0bbb-0000-714b-e31d00000000" name="FROM_HSHLD_WID" dataType="DOUBLE" precision="10" specialType="none">
</PhysicalColumn>
<PhysicalColumn mdsid="m80ca3613-0bbb-0000-714b-e31d00000000" name="FROM_ORG_WID" dataType="DOUBLE" precision="10" specialType="none">
</PhysicalColumn>
<PhysicalColumn mdsid="m80ca3614-0bbb-0000-714b-e31d00000000" name="FROM_OWNPARTY_WID" dataType="DOUBLE" precision="10" specialType="none">
</PhysicalColumn>
<PhysicalColumn mdsid="m80ca3615-0bbb-0000-714b-e31d00000000" name="FROM_SUPP_WID" dataType="DOUBLE" precision="10" specialType="none">
</PhysicalColumn>
<PhysicalColumn mdsid="m80ca3616-0bbb-0000-714b-e31d00000000" name="INTEGRATION_ID" dataType="VARCHAR" precision="30" specialType="none">
</PhysicalColumn>
<PhysicalColumn mdsid="m80ca3617-0bbb-0000-714b-e31d00000000" name="LAST_UPD_BY" dataType="VARCHAR" precision="100" nullable="true" specialType="none">
</PhysicalColumn>
<PhysicalColumn mdsid="m80ca3618-0bbb-0000-714b-e31d00000000" name="LAST_UPD_DT" dataType="DATE" nullable="true" specialType="none">
</PhysicalColumn>
<PhysicalColumn mdsid="m80ca3619-0bbb-0000-714b-e31d00000000" name="PARTY_TYPE_CD" dataType="VARCHAR" precision="30" nullable="true" specialType="none">
</PhysicalColumn>
<PhysicalColumn mdsid="m80ca361a-0bbb-0000-714b-e31d00000000" name="RELATION_CD" dataType="VARCHAR" precision="30" nullable="true" specialType="none">
</PhysicalColumn>
<PhysicalColumn mdsid="m80ca361b-0bbb-0000-714b-e31d00000000" name="RELATION_CD_I" dataType="VARCHAR" precision="50" nullable="true" specialType="none">
</PhysicalColumn>
<PhysicalColumn mdsid="m80ca361c-0bbb-0000-714b-e31d00000000" name="ROW_WID" dataType="DOUBLE" precision="10" specialType="none">
</PhysicalColumn>
<PhysicalColumn mdsid="m80ca361d-0bbb-0000-714b-e31d00000000" name="START_DT" dataType="DATE" nullable="true" specialType="none">
</PhysicalColumn>
<PhysicalColumn mdsid="m80ca361e-0bbb-0000-714b-e31d00000000" name="TO_EMP_WID" dataType="DOUBLE" precision="10" specialType="none">
</PhysicalColumn>
<PhysicalColumn mdsid="m80ca361f-0bbb-0000-714b-e31d00000000" name="TO_HSHLD_WID" dataType="DOUBLE" precision="10" specialType="none">
</PhysicalColumn>
<PhysicalColumn mdsid="m80ca3620-0bbb-0000-714b-e31d00000000" name="TO_ORG_WID" dataType="DOUBLE" precision="10" specialType="none">
</PhysicalColumn>
<PhysicalColumn mdsid="m80ca3621-0bbb-0000-714b-e31d00000000" name="TO_OWNPARTY_WID" dataType="DOUBLE" precision="10" specialType="none">
</PhysicalColumn>
<PhysicalColumn mdsid="m80ca3622-0bbb-0000-714b-e31d00000000" name="TO_SUPP_WID" dataType="DOUBLE" precision="10" specialType="none">
</PhysicalColumn>
<PhysicalColumn mdsid="m80ca3623-0bbb-0000-714b-e31d00000000" name="X_SRM_PRI_REL_FLG" dataType="CHAR" precision="1" nullable="true" specialType="none">
</PhysicalColumn>
<PhysicalColumn mdsid="m80ca3624-0bbb-0000-714b-e31d00000000" name="X_SRM_RECPRCL_CD" dataType="VARCHAR" precision="50" nullable="true" specialType="none">
</PhysicalColumn>
<PhysicalColumn mdsid="m80ca687e-0bbb-0000-714b-e31d00000000" name="RECIPROCAL_REL_FLG" dataType="CHAR" precision="1" specialType="none">
</PhysicalColumn>
<PhysicalKey mdsid="m80ca365c-0bc0-0000-714b-e31d00000000" name="ROW_WID">
<RefColumns>
<RefColumn refId="m80ca365c-0bc0-0000-714b-e31d00000000-m80ca361c-0bbb-0000-714b-e31d00000000" columnRef="/oracle/bi/server/base/PhysicalTable/80ca360a-0bb9-0000-714b-e31d00000000.xml#m80ca361c-0bbb-0000-714b-e31d00000000"/>
</RefColumns>
</PhysicalKey>
</PhysicalTable>